src/demo.py
lambdatesting2323232323-0.1.dist-info/METADATA
lambdatesting2323232323-0.1.dist-info/WHEEL
lambdatesting2323232323-0.1.dist-info/top_level.txt
lambdatesting2323232323-0.1.dist-info/RECORD
