Metadata-Version: 2.1
Name: lambdatesting2323232323
Version: 0.1
Summary: Example inherits package
Home-page: UNKNOWN
Author: FMU
Author-email: UNKNOWN
License: UNKNOWN
Platform: UNKNOWN
